fnc/__init__.py
fnc/helpers.py
fnc/mappings.py
fnc/sequences.py
fnc/utilities.py
fnc-0.5.3.dist-info/AUTHORS.rst
fnc-0.5.3.dist-info/LICENSE.rst
fnc-0.5.3.dist-info/METADATA
fnc-0.5.3.dist-info/WHEEL
fnc-0.5.3.dist-info/top_level.txt
fnc-0.5.3.dist-info/RECORD
